pointless.cpython-310-darwin.so
tests/compile.sh
tests/__init__.py
tests/scc.py
tests/test_intop_eval.c
tests/run_recreate_test.sh
tests/python_api/test_print.py
tests/python_api/test_pypointless.py
tests/python_api/__init__.py
tests/python_api/common.py
tests/python_api/test_thread_safe_sort.py
tests/python_api/test_serialize.py
tests/python_api/test_primvector.py
tests/python_api/test_set_map.py
tests/python_api/test_cmp.py
tests/python_api/test_thread_safe.py
tests/c_api/test.h
tests/c_api/create.c
tests/c_api/main.c
tests/c_api/validate_hash.c
tests/c_api/performance_test.c
pointless-1.0.28.dist-info/RECORD
pointless-1.0.28.dist-info/WHEEL
pointless-1.0.28.dist-info/top_level.txt
pointless-1.0.28.dist-info/METADATA
