Metadata-Version: 2.4
Name: pointless
Version: 1.0.28
Summary: A read-only relocatable data structure for JSON like data, with C and Python APIs
Author-email: Arni Mar Jonsson <arnimarj@gmail.com>
Project-URL: Source Code, https://github.com/arnimarj/py-pointless
Classifier: Development Status :: 5 - Production/Stable
Classifier: Environment :: Other Environment
Classifier: Intended Audience :: Developers
Classifier: License :: OSI Approved :: GNU Library or Lesser General Public License (LGPL)
Classifier: Operating System :: POSIX
Classifier: Programming Language :: C
Classifier: Programming Language :: Python
Classifier: Programming Language :: Python :: 3
Classifier: Programming Language :: Python :: 3.9
Classifier: Programming Language :: Python :: 3.10
Classifier: Programming Language :: Python :: 3.11
Classifier: Programming Language :: Python :: 3.12
Classifier: Programming Language :: Python :: 3.13
Classifier: Topic :: Database
Classifier: Topic :: Software Development :: Libraries
Requires-Python: >=3.9
